{
    "hparam": {
        "model_name_or_path": "meta-llama/Meta-Llama-3-8B",
        "h_dim": 512,
        "n_injector_head": 4,
        "injector_dropout_p": 0.1,
        "encoder_dropout_p": 0.1,
        "n_encoder_head": 4,
        "n_encoder_layers": 6,
        "to_matrix": "outer_product"
    },
    "evaluation_metrics": {
        "test_time": 449.7413692474365,
        "test_sg_loss": 0.31654314011849005,
        "test_sg_accuracy": 0.9449769854545593,
        "test_sg_precision": 0.47249823808670044,
        "test_sg_recall": 0.4999890923500061,
        "test_sg_f1": 0.48585510125228754,
        "test_gg_loss": 0.896653855697022,
        "test_gg_accuracy": 0.0011165841715410352,
        "test_gg_precision": 0.5001412598358002,
        "test_gg_recall": 0.5000211602236959,
        "test_gg_f1": 0.0011159025193907286
    },
    "history": [
        {
            "epoch": 1,
            "train_time": 501.7889528274536,
            "train_sg_loss": 0.27377314256491314,
            "train_sg_accuracy": 0.9197652339935303,
            "train_sg_precision": 0.530887559056282,
            "train_sg_recall": 0.5095495209097862,
            "train_sg_f1": 0.5077950007653187,
            "train_gg_loss": 0.8504392156261876,
            "train_gg_accuracy": 0.26224157214164734,
            "train_gg_precision": 0.5001610486651771,
            "train_gg_recall": 0.531864583492279,
            "train_gg_f1": 0.20845549377801428,
            "val_time": 430.458753824234,
            "val_sg_loss": 0.6277501080906295,
            "val_sg_accuracy": 0.9346504211425781,
            "val_sg_precision": 0.4821226056665182,
            "val_sg_recall": 0.49512104596942663,
            "val_sg_f1": 0.48661213737835496,
            "val_gg_loss": 1.438197801189991,
            "val_gg_accuracy": 0.0010271877981722355,
            "val_gg_precision": 0.0005135938990861177,
            "val_gg_recall": 0.5,
            "val_gg_f1": 0.001026133766088417
        },
        {
            "epoch": 2,
            "train_time": 501.2859060764313,
            "train_sg_loss": 0.20838071739070907,
            "train_sg_accuracy": 0.9298853278160095,
            "train_sg_precision": 0.5513171926140785,
            "train_sg_recall": 0.5054379971697927,
            "train_sg_f1": 0.4970130921080873,
            "train_gg_loss": 0.7717185570673325,
            "train_gg_accuracy": 0.2626930773258209,
            "train_gg_precision": 0.5001580370590091,
            "train_gg_recall": 0.5313033014535904,
            "train_gg_f1": 0.20873855026470262,
            "val_time": 430.7482478618622,
            "val_sg_loss": 0.3730652992623419,
            "val_sg_accuracy": 0.9476322531700134,
            "val_sg_precision": 0.5406109169125557,
            "val_sg_recall": 0.5002584266185295,
            "val_sg_f1": 0.48735514434056515,
            "val_gg_loss": 1.0965191667791558,
            "val_gg_accuracy": 0.0026112913619726896,
            "val_gg_precision": 0.5004054878372699,
            "val_gg_recall": 0.500625251675956,
            "val_gg_f1": 0.002610981297283598
        },
        {
            "epoch": 3,
            "train_time": 500.26245379447937,
            "train_sg_loss": 0.17871959066002122,
            "train_sg_accuracy": 0.932643473148346,
            "train_sg_precision": 0.6135015338659286,
            "train_sg_recall": 0.5070607280358672,
            "train_sg_f1": 0.49864435296886533,
            "train_gg_loss": 0.7544627291165933,
            "train_gg_accuracy": 0.2803863286972046,
            "train_gg_precision": 0.500182943069376,
            "train_gg_recall": 0.5377553403377533,
            "train_gg_f1": 0.21972229651307906,
            "val_time": 428.6998517513275,
            "val_sg_loss": 0.17082124624255546,
            "val_sg_accuracy": 0.9478419423103333,
            "val_sg_precision": 0.4739309251308441,
            "val_sg_recall": 0.49998894333839417,
            "val_sg_f1": 0.4866113324990512,
            "val_gg_loss": 0.7446333231259975,
            "val_gg_accuracy": 0.13699662685394287,
            "val_gg_precision": 0.500476035871543,
            "val_gg_recall": 0.5545204877853394,
            "val_gg_f1": 0.12097693928635685
        },
        {
            "epoch": 4,
            "train_time": 501.0088748931885,
            "train_sg_loss": 0.15833513821996076,
            "train_sg_accuracy": 0.9345721006393433,
            "train_sg_precision": 0.7561340928077698,
            "train_sg_recall": 0.5089723970741034,
            "train_sg_f1": 0.5013886568373637,
            "train_gg_loss": 0.7400495031244159,
            "train_gg_accuracy": 0.3062949776649475,
            "train_gg_precision": 0.5001832522102632,
            "train_gg_recall": 0.5398352593183517,
            "train_gg_f1": 0.23525625198041863,
            "val_time": 429.4624936580658,
            "val_sg_loss": 0.1565145671912665,
            "val_sg_accuracy": 0.9478419423103333,
            "val_sg_precision": 0.4739309251308441,
            "val_sg_recall": 0.49998894333839417,
            "val_sg_f1": 0.4866113324990512,
            "val_gg_loss": 0.7092887634448107,
            "val_gg_accuracy": 0.2182701677083969,
            "val_gg_precision": 0.5004426582017913,
            "val_gg_recall": 0.5733893513679504,
            "val_gg_f1": 0.17987852670021648
        },
        {
            "epoch": 5,
            "train_time": 499.75040769577026,
            "train_sg_loss": 0.19767865259132736,
            "train_sg_accuracy": 0.9286203384399414,
            "train_sg_precision": 0.570834182202816,
            "train_sg_recall": 0.5109173562377691,
            "train_sg_f1": 0.5076131255168053,
            "train_gg_loss": 0.7638488050851305,
            "train_gg_accuracy": 0.2962346076965332,
            "train_gg_precision": 0.5002068125759251,
            "train_gg_recall": 0.5441023260354996,
            "train_gg_f1": 0.22930809991098328,
            "val_time": 431.7507691383362,
            "val_sg_loss": 0.30247576145952837,
            "val_sg_accuracy": 0.9478839039802551,
            "val_sg_precision": 0.9739414155483246,
            "val_sg_recall": 0.5002011263131863,
            "val_sg_f1": 0.48702418948502235,
            "val_gg_loss": 0.8975170966245797,
            "val_gg_accuracy": 0.001262237667106092,
            "val_gg_precision": 0.500101868994534,
            "val_gg_recall": 0.5000233588507399,
            "val_gg_f1": 0.001261611557380516
        }
    ]
}