{
    "hparam": {
        "model_name_or_path": "meta-llama/Meta-Llama-3-8B",
        "h_dim": 256,
        "n_injector_head": 4,
        "injector_dropout_p": 0.1,
        "encoder_dropout_p": 0.1,
        "n_encoder_head": 8,
        "n_encoder_layers": 6,
        "to_matrix": "diagonal"
    },
    "evaluation_metrics": {
        "test_time": 453.1324768066406,
        "test_sg_loss": 0.15214325920906097,
        "test_sg_accuracy": 0.944111168384552,
        "test_sg_precision": 0.601899266242981,
        "test_sg_recall": 0.5035904399119318,
        "test_sg_f1": 0.49396151243432906,
        "test_gg_loss": 0.007312582196614121,
        "test_gg_accuracy": 0.9990285038948059,
        "test_gg_precision": 0.49951431155204773,
        "test_gg_recall": 0.5,
        "test_gg_f1": 0.4997570377720765
    },
    "history": [
        {
            "epoch": 1,
            "train_time": 510.09093618392944,
            "train_sg_loss": 0.27001392747355124,
            "train_sg_accuracy": 0.8957508206367493,
            "train_sg_precision": 0.5896952897310257,
            "train_sg_recall": 0.5973976999521255,
            "train_sg_f1": 0.5933013066289881,
            "train_gg_loss": 0.12950874192128278,
            "train_gg_accuracy": 0.9609414935112,
            "train_gg_precision": 0.5018667958211154,
            "train_gg_recall": 0.5706478953361511,
            "train_gg_f1": 0.49449334145031404,
            "val_time": 433.56090259552,
            "val_sg_loss": 0.14846902992736521,
            "val_sg_accuracy": 0.9471498727798462,
            "val_sg_precision": 0.5774739757180214,
            "val_sg_recall": 0.5019046112429351,
            "val_sg_f1": 0.4911423133146513,
            "val_gg_loss": 0.0073793507253004,
            "val_gg_accuracy": 0.9989727735519409,
            "val_gg_precision": 0.49948638677597046,
            "val_gg_recall": 0.5,
            "val_gg_f1": 0.4997430614209333
        },
        {
            "epoch": 2,
            "train_time": 510.6893494129181,
            "train_sg_loss": 0.18923731632690607,
            "train_sg_accuracy": 0.9321457743644714,
            "train_sg_precision": 0.6163151264190674,
            "train_sg_recall": 0.5097259664908051,
            "train_sg_f1": 0.5040501902751843,
            "train_gg_loss": 0.008387200006592448,
            "train_gg_accuracy": 0.9990225434303284,
            "train_gg_precision": 0.4995112717151642,
            "train_gg_recall": 0.5,
            "train_gg_f1": 0.49975551637151766,
            "val_time": 433.7610719203949,
            "val_sg_loss": 0.14490697357706236,
            "val_sg_accuracy": 0.9476322531700134,
            "val_sg_precision": 0.5123963691294193,
            "val_sg_recall": 0.5000683569669491,
            "val_sg_f1": 0.48695589939535294,
            "val_gg_loss": 0.007466188516254378,
            "val_gg_accuracy": 0.9989727735519409,
            "val_gg_precision": 0.49948638677597046,
            "val_gg_recall": 0.5,
            "val_gg_f1": 0.4997430614209333
        },
        {
            "epoch": 3,
            "train_time": 507.9290843009949,
            "train_sg_loss": 0.18125373821162713,
            "train_sg_accuracy": 0.9326849579811096,
            "train_sg_precision": 0.6477133184671402,
            "train_sg_recall": 0.5132392793893814,
            "train_sg_f1": 0.5104723503832996,
            "train_gg_loss": 0.00830336872454194,
            "train_gg_accuracy": 0.9990225434303284,
            "train_gg_precision": 0.4995112717151642,
            "train_gg_recall": 0.5,
            "train_gg_f1": 0.49975551637151766,
            "val_time": 434.02742648124695,
            "val_sg_loss": 0.14507703898869667,
            "val_sg_accuracy": 0.9477580785751343,
            "val_sg_precision": 0.4739287197589874,
            "val_sg_recall": 0.49994468688964844,
            "val_sg_f1": 0.48658920921413745,
            "val_gg_loss": 0.007542151070902195,
            "val_gg_accuracy": 0.9989727735519409,
            "val_gg_precision": 0.49948638677597046,
            "val_gg_recall": 0.5,
            "val_gg_f1": 0.4997430614209333
        },
        {
            "epoch": 4,
            "train_time": 510.3829679489136,
            "train_sg_loss": 0.1710940552585502,
            "train_sg_accuracy": 0.9358370900154114,
            "train_sg_precision": 0.7721995115280151,
            "train_sg_recall": 0.5331022515892982,
            "train_sg_f1": 0.5456015241795739,
            "train_gg_loss": 0.008480424136254782,
            "train_gg_accuracy": 0.9990224838256836,
            "train_gg_precision": 0.4995112717151642,
            "train_gg_recall": 0.4999999701976776,
            "train_gg_f1": 0.4997555014849248,
            "val_time": 433.81064653396606,
            "val_sg_loss": 0.145968457291563,
            "val_sg_accuracy": 0.947296679019928,
            "val_sg_precision": 0.5593483373522758,
            "val_sg_recall": 0.5010317490668967,
            "val_sg_f1": 0.4892356050721274,
            "val_gg_loss": 0.007581581241746153,
            "val_gg_accuracy": 0.9989727735519409,
            "val_gg_precision": 0.49948638677597046,
            "val_gg_recall": 0.5,
            "val_gg_f1": 0.4997430614209333
        },
        {
            "epoch": 5,
            "train_time": 508.79541087150574,
            "train_sg_loss": 0.16531463903060062,
            "train_sg_accuracy": 0.9370605945587158,
            "train_sg_precision": 0.7971038222312927,
            "train_sg_recall": 0.5437245219945908,
            "train_sg_f1": 0.5634093895347518,
            "train_gg_loss": 0.008650196793695709,
            "train_gg_accuracy": 0.9990217685699463,
            "train_gg_precision": 0.5595113299787045,
            "train_gg_recall": 0.5000617665209575,
            "train_gg_f1": 0.4998796211316493,
            "val_time": 436.0053777694702,
            "val_sg_loss": 0.1468019222871996,
            "val_sg_accuracy": 0.9469401240348816,
            "val_sg_precision": 0.5039356034249067,
            "val_sg_recall": 0.5000834178063087,
            "val_sg_f1": 0.48755561745785025,
            "val_gg_loss": 0.007692969508499277,
            "val_gg_accuracy": 0.9989726543426514,
            "val_gg_precision": 0.5709149911999702,
            "val_gg_recall": 0.500010456335076,
            "val_gg_f1": 0.49976403064795566
        }
    ]
}